rustfs_s3_toolkit/__init__.py
rustfs_s3_toolkit/s3_client.py
rustfs_s3_toolkit-0.2.0.dist-info/licenses/LICENSE
rustfs_s3_toolkit-0.2.0.dist-info/METADATA
rustfs_s3_toolkit-0.2.0.dist-info/WHEEL
rustfs_s3_toolkit-0.2.0.dist-info/top_level.txt
rustfs_s3_toolkit-0.2.0.dist-info/RECORD
