Metadata-Version: 2.4
Name: rustfs-s3-toolkit
Version: 0.2.0
Summary: RustFS S3 Storage Toolkit - A simple and powerful toolkit for RustFS and other S3-compatible object storage operations
Author-email: mm644706215 <ze.ga@qq.com>
Project-URL: Homepage, https://github.com/mm644706215/rustfs-s3-toolkit
Project-URL: Repository, https://github.com/mm644706215/rustfs-s3-toolkit
Project-URL: Documentation, https://github.com/mm644706215/rustfs-s3-toolkit#readme
Project-URL: Issues, https://github.com/mm644706215/rustfs-s3-toolkit/issues
Keywords: rustfs,s3,object-storage,file-management,cloud-storage,toolkit
Classifier: Development Status :: 4 - Beta
Classifier: Intended Audience :: Developers
Classifier: Programming Language :: Python :: 3
Classifier: Programming Language :: Python :: 3.9
Classifier: Programming Language :: Python :: 3.10
Classifier: Programming Language :: Python :: 3.11
Classifier: Programming Language :: Python :: 3.12
Classifier: Programming Language :: Python :: 3.13
Classifier: Topic :: Software Development :: Libraries :: Python Modules
Classifier: Topic :: System :: Archiving
Classifier: Topic :: Internet :: File Transfer Protocol (FTP)
Classifier: Topic :: System :: Filesystems
Requires-Python: >=3.9
License-File: LICENSE
Requires-Dist: boto3>=1.39.0
Provides-Extra: dev
Requires-Dist: pytest>=7.0.0; extra == "dev"
Requires-Dist: pytest-asyncio>=0.21.0; extra == "dev"
Requires-Dist: black>=23.0.0; extra == "dev"
Requires-Dist: isort>=5.12.0; extra == "dev"
Requires-Dist: flake8>=6.0.0; extra == "dev"
Requires-Dist: mypy>=1.0.0; extra == "dev"
Dynamic: license-file
